yt_transcriptor/__init__.py
yt_transcriptor/cli.py
yt_transcriptor/core.py
yt_transcriptor-0.1.1.dist-info/METADATA
yt_transcriptor-0.1.1.dist-info/WHEEL
yt_transcriptor-0.1.1.dist-info/entry_points.txt
yt_transcriptor-0.1.1.dist-info/top_level.txt
yt_transcriptor-0.1.1.dist-info/RECORD
