Metadata-Version: 2.4
Name: yt-transcriptor
Version: 0.1.1
Author: Tin Rabzelj
Project-URL: Homepage, https://github.com/tinrab/yt-transcriptor
Project-URL: Issues, https://github.com/tinrab/yt-transcriptor/issues
Requires-Python: >=3.8
Requires-Dist: click
Requires-Dist: openai-whisper>=20240930
Requires-Dist: yt-dlp>=2024.10.22
